Workbook

Sheet Assumptions
A1: ITS — FINANCIAL PROJECTION ASSUMPTIONS
A2: Edit these inputs — all scenario sheets update automatically.
A4: Parameter | B4: Value | C4: Unit | D4: Notes
A5: Standard Hourly Rate | B5: 1000 | C5: DA/hr | D5: From Pricing Calculator
A6: Emergency Hourly Rate | B6: 1500 | C6: DA/hr | D6: 1.5x multiplier
A7: Dispatch Fee | B7: 2000 | C7: DA | D7: Flat fee
A8: Minimum Call-Out | B8: 2500 | C8: DA | D8: Non-emergency minimum
A9: Materials Markup % | B9: 0.15 | C9: % | D9: Default markup on parts
A10: Target Profit Margin % | B10: 0.25 | C10: % | D10: Net margin target
A11: SLA Basic Rate | B11: 6000 | C11: DA/mo | D11: Monthly retainer
A12: SLA Standard Rate | B12: 10000 | C12: DA/mo | D12: Monthly retainer
A13: SLA Comprehensive Rate | B13: 16000 | C13: DA/mo | D13: Monthly retainer
A14: Workshop Rent | B14: 0 | C14: DA/mo | D14: ENTER YOUR ACTUAL COST
A15: Utilities | B15: 0 | C15: DA/mo | D15: ENTER YOUR ACTUAL COST
A16: Lead Engineer Salary | B16: 0 | C16: DA/mo | D16: ENTER YOUR ACTUAL COST
... A23: Miscellaneous | B23: 0 | C23: DA/mo | D23: ENTER YOUR ACTUAL COST
A25: TOTAL MONTHLY FIXED COSTS | B25: =SUM(B14:B23) -> 0

Sheet Conservative
A1: SCENARIO 1: CONSERVATIVE — 3 Projects + 1 SLA
A2: All formulas reference the 'Assumptions' sheet. Change assumptions once, all scenarios update.
A4: Month | B4: Project Hours | C4: Project Revenue (DA) | D4: Emergency Hours | E4: Emergency Revenue (DA) | F4: SLA Revenue (DA) | G4: Total Revenue (DA)
B5: Fixed Hours | C5: From Projects | D5: Emergency | E5: Emergency Billing | F5: SLA Retainers | G5: Monthly Total
A6: Month 1 | B6: 20 | C6: =B6*Assumptions!B5+Assumptions!B9*B6*Assumptions!B5 -> 23000 | D6: 2 | E6: =D6*Assumptions!B6+Assumptions!B7 -> 5000 | F6: 6000 | G6: =C6+E6+F6 -> 34000
A7: Month 2 | B7: 25 | C7: =B7*Assumptions!B5+Assumptions!B9*B7*Assumptions!B5 -> 28750 | D7: 3 | E7: =D7*Assumptions!B6+Assumptions!B7 -> 6500 | F7: 6000 | G7: =C7+E7+F7 -> 41250
A8: Month 3 | B8: 20 | C8: =B8*Assumptions!B5+Assumptions!B9*B8*Assumptions!B5 -> 23000 | D8: 2 | E8: =D8*Assumptions!B6+Assumptions!B7 -> 5000 | F8: 6000 | G8: =C8+E8+F8 -> 34000
A9: Month 4 | B9: 30 | C9: =B9*Assumptions!B5+Assumptions!B9*B9*Assumptions!B5 -> 34500 | D9: 4 | E9: =D9*Assumptions!B6+Assumptions!B7 -> 8000 | F9: 6000 | G9: =C9+E9+F9 -> 48500
A10: Month 5 | B10: 25 | C10: =B10*Assumptions!B5+Assumptions!B9*B10*Assumptions!B5 -> 28750 | D10: 3 | E10: =D10*Assumptions!B6+Assumptions!B7 -> 6500 | F10: 6000 | G10: =C10+E10+F10 -> 41250
A11: Month 6 | B11: 20 | C11: =B11*Assumptions!B5+Assumptions!B9*B11*Assumptions!B5 -> 23000 | D11: 2 | E11: =D11*Assumptions!B6+Assumptions!B7 -> 5000 | F11: 6000 | G11: =C11+E11+F11 -> 34000
A13: 6-MONTH TOTAL | B13: =SUM(B6:B11) -> 140 | C13: =SUM(C6:C11) -> 161000 | D13: =SUM(D6:D11) -> 16 | E13: =SUM(E6:E11) -> 36000 | F13: =SUM(F6:F11) -> 36000 | G13: =SUM(G6:G11) -> 233000
A14: Monthly Average | B14: =B13/6 -> 23.333333 | C14: =B13/6 -> 23.333333 | D14: =B13/6 -> 23.333333 | E14: =B13/6 -> 23.333333 | F14: =B13/6 -> 23.333333 | G14: =B13/6 -> 23.333333
A16: COSTS & PROFIT
A17: Total 6-Month Fixed Costs | B17: =Assumptions!B25*6 -> 0
A18: Total 6-Month Variable Costs (est. 30% of project rev) | B18: =C13*0.3 -> 48300
A19: Gross Profit | B19: =G13-B17-B18 -> 184700
A20: Profit Margin | B20: =IF(G13>0,B19/G13,0) -> 0.79270386
A22: MONTHLY CASH FLOW
A23: Month | B23: Revenue | C23: Fixed Costs | D23: Variable Costs (est.) | E23: Net Cash Flow | F23: Cumulative
A24: Month 1 | B24: =G6 -> 34000 | C24: =Assumptions!B25/6 -> 0 | D24: =B24*0.3 -> 10200 | E24: =B24-C24-D24 -> 23800 | F24: =E24 -> 23800
A25: Month 2 | B25: =G7 -> 41250 | C25: =Assumptions!B25/6 -> 0 | D25: =B25*0.3 -> 12375 | E25: =B25-C25-D25 -> 28875 | F25: =F24+E25 -> 52675
A26: Month 3 | B26: =G8 -> 34000 | C26: =Assumptions!B25/6 -> 0 | D26: =B26*0.3 -> 10200 | E26: =B26-C26-D26 -> 23800 | F26: =F25+E26 -> 76475
A27: Month 4 | B27: =G9 -> 48500 | C27: =Assumptions!B25/6 -> 0 | D27: =B27*0.3 -> 14550 | E27: =B27-C27-D27 -> 33950 | F27: =F26+E27 -> 110425
A28: Month 5 | B28: =G10 -> 41250 | C28: =Assumptions!B25/6 -> 0 | D28: =B28*0.3 -> 12375 | E28: =B28-C28-D28 -> 28875 | F28: =F27+E28 -> 139300
A29: Month 6 | B29: =G11 -> 34000 | C29: =Assumptions!B25/6 -> 0 | D29: =B29*0.3 -> 10200 | E29: =B29-C29-D29 -> 23800 | F29: =F28+E29 -> 163100

Sheet Moderate
A1: SCENARIO 2: MODERATE — 5 Projects + 2 SLAs
A2: All formulas reference the 'Assumptions' sheet. Change assumptions once, all scenarios update.
A4: Month | B4: Project Hours | C4: Project Revenue (DA) | D4: Emergency Hours | E4: Emergency Revenue (DA) | F4: SLA Revenue (DA) | G4: Total Revenue (DA)
B5: Fixed Hours | C5: From Projects | D5: Emergency | E5: Emergency Billing | F5: SLA Retainers | G5: Monthly Total
A6: Month 1 | B6: 30 | C6: =B6*Assumptions!B5+Assumptions!B9*B6*Assumptions!B5 -> 34500 | D6: 3 | E6: =D6*Assumptions!B6+Assumptions!B7 -> 6500 | F6: 16000 | G6: =C6+E6+F6 -> 57000
A7: Month 2 | B7: 40 | C7: =B7*Assumptions!B5+Assumptions!B9*B7*Assumptions!B5 -> 46000 | D7: 5 | E7: =D7*Assumptions!B6+Assumptions!B7 -> 9500 | F7: 16000 | G7: =C7+E7+F7 -> 71500
A8: Month 3 | B8: 35 | C8: =B8*Assumptions!B5+Assumptions!B9*B8*Assumptions!B5 -> 40250 | D8: 3 | E8: =D8*Assumptions!B6+Assumptions!B7 -> 6500 | F8: 16000 | G8: =C8+E8+F8 -> 62750
A9: Month 4 | B9: 45 | C9: =B9*Assumptions!B5+Assumptions!B9*B9*Assumptions!B5 -> 51750 | D9: 6 | E9: =D9*Assumptions!B6+Assumptions!B7 -> 11000 | F9: 16000 | G9: =C9+E9+F9 -> 78750
A10: Month 5 | B10: 40 | C10: =B10*Assumptions!B5+Assumptions!B9*B10*Assumptions!B5 -> 46000 | D10: 4 | E10: =D10*Assumptions!B6+Assumptions!B7 -> 8000 | F10: 16000 | G10: =C10+E10+F10 -> 70000
A11: Month 6 | B11: 35 | C11: =B11*Assumptions!B5+Assumptions!B9*B11*Assumptions!B5 -> 40250 | D11: 3 | E11: =D11*Assumptions!B6+Assumptions!B7 -> 6500 | F11: 16000 | G11: =C11+E11+F11 -> 62750
A13: 6-MONTH TOTAL | B13: =SUM(B6:B11) -> 225 | C13: =SUM(C6:C11) -> 258750 | D13: =SUM(D6:D11) -> 24 | E13: =SUM(E6:E11) -> 48000 | F13: =SUM(F6:F11) -> 96000 | G13: =SUM(G6:G11) -> 402750
A14: Monthly Average | B14: =B13/6 -> 37.5 | C14: =B13/6 -> 37.5 | D14: =B13/6 -> 37.5 | E14: =B13/6 -> 37.5 | F14: =B13/6 -> 37.5 | G14: =B13/6 -> 37.5
A16: COSTS & PROFIT
A17: Total 6-Month Fixed Costs | B17: =Assumptions!B25*6 -> 0
A18: Total 6-Month Variable Costs (est. 30% of project rev) | B18: =C13*0.3 -> 77625
A19: Gross Profit | B19: =G13-B17-B18 -> 325125
A20: Profit Margin | B20: =IF(G13>0,B19/G13,0) -> 0.80726257
A22: MONTHLY CASH FLOW
A23: Month | B23: Revenue | C23: Fixed Costs | D23: Variable Costs (est.) | E23: Net Cash Flow | F23: Cumulative
A24: Month 1 | B24: =G6 -> 57000 | C24: =Assumptions!B25/6 -> 0 | D24: =B24*0.3 -> 17100 | E24: =B24-C24-D24 -> 39900 | F24: =E24 -> 39900
A25: Month 2 | B25: =G7 -> 71500 | C25: =Assumptions!B25/6 -> 0 | D25: =B25*0.3 -> 21450 | E25: =B25-C25-D25 -> 50050 | F25: =F24+E25 -> 89950
A26: Month 3 | B26: =G8 -> 62750 | C26: =Assumptions!B25/6 -> 0 | D26: =B26*0.3 -> 18825 | E26: =B26-C26-D26 -> 43925 | F26: =F25+E26 -> 133875
A27: Month 4 | B27: =G9 -> 78750 | C27: =Assumptions!B25/6 -> 0 | D27: =B27*0.3 -> 23625 | E27: =B27-C27-D27 -> 55125 | F27: =F26+E27 -> 189000
A28: Month 5 | B28: =G10 -> 70000 | C28: =Assumptions!B25/6 -> 0 | D28: =B28*0.3 -> 21000 | E28: =B28-C28-D28 -> 49000 | F28: =F27+E28 -> 238000
A29: Month 6 | B29: =G11 -> 62750 | C29: =Assumptions!B25/6 -> 0 | D29: =B29*0.3 -> 18825 | E29: =B29-C29-D29 -> 43925 | F29: =F28+E29 -> 281925

Sheet Optimistic
A1: SCENARIO 3: OPTIMISTIC — 8 Projects + 4 SLAs
A2: All formulas reference the 'Assumptions' sheet. Change assumptions once, all scenarios update.
A4: Month | B4: Project Hours | C4: Project Revenue (DA) | D4: Emergency Hours | E4: Emergency Revenue (DA) | F4: SLA Revenue (DA) | G4: Total Revenue (DA)
B5: Fixed Hours | C5: From Projects | D5: Emergency | E5: Emergency Billing | F5: SLA Retainers | G5: Monthly Total
A6: Month 1 | B6: 45 | C6: =B6*Assumptions!B5+Assumptions!B9*B6*Assumptions!B5 -> 51750 | D6: 5 | E6: =D6*Assumptions!B6+Assumptions!B7 -> 9500 | F6: 32000 | G6: =C6+E6+F6 -> 93250
A7: Month 2 | B7: 55 | C7: =B7*Assumptions!B5+Assumptions!B9*B7*Assumptions!B5 -> 63250 | D7: 8 | E7: =D7*Assumptions!B6+Assumptions!B7 -> 14000 | F7: 32000 | G7: =C7+E7+F7 -> 109250
A8: Month 3 | B8: 50 | C8: =B8*Assumptions!B5+Assumptions!B9*B8*Assumptions!B5 -> 57500 | D8: 5 | E8: =D8*Assumptions!B6+Assumptions!B7 -> 9500 | F8: 32000 | G8: =C8+E8+F8 -> 99000
A9: Month 4 | B9: 65 | C9: =B9*Assumptions!B5+Assumptions!B9*B9*Assumptions!B5 -> 74750 | D9: 10 | E9: =D9*Assumptions!B6+Assumptions!B7 -> 17000 | F9: 32000 | G9: =C9+E9+F9 -> 123750
A10: Month 5 | B10: 60 | C10: =B10*Assumptions!B5+Assumptions!B9*B10*Assumptions!B5 -> 69000 | D10: 6 | E10: =D10*Assumptions!B6+Assumptions!B7 -> 11000 | F10: 32000 | G10: =C10+E10+F10 -> 112000
A11: Month 6 | B11: 50 | C11: =B11*Assumptions!B5+Assumptions!B9*B11*Assumptions!B5 -> 57500 | D11: 5 | E11: =D11*Assumptions!B6+Assumptions!B7 -> 9500 | F11: 32000 | G11: =C11+E11+F11 -> 99000
A13: 6-MONTH TOTAL | B13: =SUM(B6:B11) -> 325 | C13: =SUM(C6:C11) -> 373750 | D13: =SUM(D6:D11) -> 39 | E13: =SUM(E6:E11) -> 70500 | F13: =SUM(F6:F11) -> 192000 | G13: =SUM(G6:G11) -> 636250
A14: Monthly Average | B14: =B13/6 -> 54.166667 | C14: =B13/6 -> 54.166667 | D14: =B13/6 -> 54.166667 | E14: =B13/6 -> 54.166667 | F14: =B13/6 -> 54.166667 | G14: =B13/6 -> 54.166667
A16: COSTS & PROFIT
A17: Total 6-Month Fixed Costs | B17: =Assumptions!B25*6 -> 0
A18: Total 6-Month Variable Costs (est. 30% of project rev) | B18: =C13*0.3 -> 112125
A19: Gross Profit | B19: =G13-B17-B18 -> 524125
A20: Profit Margin | B20: =IF(G13>0,B19/G13,0) -> 0.8237721
A22: MONTHLY CASH FLOW
A23: Month | B23: Revenue | C23: Fixed Costs | D23: Variable Costs (est.) | E23: Net Cash Flow | F23: Cumulative
A24: Month 1 | B24: =G6 -> 93250 | C24: =Assumptions!B25/6 -> 0 | D24: =B24*0.3 -> 27975 | E24: =B24-C24-D24 -> 65275 | F24: =E24 -> 65275
A25: Month 2 | B25: =G7 -> 109250 | C25: =Assumptions!B25/6 -> 0 | D25: =B25*0.3 -> 32775 | E25: =B25-C25-D25 -> 76475 | F25: =F24+E25 -> 141750
A26: Month 3 | B26: =G8 -> 99000 | C26: =Assumptions!B25/6 -> 0 | D26: =B26*0.3 -> 29700 | E26: =B26-C26-D26 -> 69300 | F26: =F25+E26 -> 211050
A27: Month 4 | B27: =G9 -> 123750 | C27: =Assumptions!B25/6 -> 0 | D27: =B27*0.3 -> 37125 | E27: =B27-C27-D27 -> 86625 | F27: =F26+E27 -> 297675
A28: Month 5 | B28: =G10 -> 112000 | C28: =Assumptions!B25/6 -> 0 | D28: =B28*0.3 -> 33600 | E28: =B28-C28-D28 -> 78400 | F28: =F27+E28 -> 376075
A29: Month 6 | B29: =G11 -> 99000 | C29: =Assumptions!B25/6 -> 0 | D29: =B29*0.3 -> 29700 | E29: =B29-C29-D29 -> 69300 | F29: =F28+E29 -> 445375

Sheet Summary Dashboard
A1: ITS — 6-MONTH FINANCIAL PROJECTION SUMMARY
A3: Metric | B3: Conservative | C3: Moderate | D3: Optimistic | E3: Notes
A4: Total Revenue (6 months) | B4: =Conservative!G13 -> 233000 | C4: =Moderate!G13 -> 402750 | D4: =Optimistic!G13 -> 636250 | E4: Top-line revenue
A5: Total Fixed Costs (6 mo) | B5: =Conservative!B17 -> 0 | C5: =Moderate!B17 -> 0 | D5: =Optimistic!B17 -> 0 | E5: From Assumptions sheet
A6: Total Variable Costs | B6: =Conservative!B18 -> 48300 | C6: =Moderate!B18 -> 77625 | D6: =Optimistic!B18 -> 112125 | E6: Estimated 30% of project rev
A7: Gross Profit | B7: =Conservative!B19 -> 184700 | C7: =Moderate!B19 -> 325125 | D7: =Optimistic!B19 -> 524125 | E7: Revenue - All costs
A8: Profit Margin | B8: =Conservative!B20 -> 0.79270386 | C8: =Moderate!B20 -> 0.80726257 | D8: =Optimistic!B20 -> 0.8237721 | E8: Margin %
A9: Total Project Hours | B9: =Conservative!B13 -> 140 | C9: =Moderate!B13 -> 225 | D9: =Optimistic!B13 -> 325 | E9: Billable hours
A10: Avg Monthly Revenue | B10: =Conservative!G14 -> 23.333333 | C10: =Moderate!G14 -> 37.5 | D10: =Optimistic!G14 -> 54.166667 | E10: Monthly average
A11: Avg Monthly Hours | B11: =Conservative!B14 -> 23.333333 | C11: =Moderate!B14 -> 37.5 | D11: =Optimistic!B14 -> 54.166667 | E11: Monthly average
A12: Breakeven Hours/Month | B12: =Assumptions!B25/Assumptions!B5 -> 0 | C12: =Assumptions!B25/Assumptions!B5 -> 0 | D12: =Assumptions!B25/Assumptions!B5 -> 0 | E12: Fixed costs / hourly rate
A15: VERDICT: Is ITS viable?
A16: Break-even monthly hours: | B16: =Assumptions!B25/Assumptions!B5 -> 0 | C16: hours/month needed to cover fixed costs
A17: Conservative scenario covers costs? | B17: =IF(Conservative!B19>0,"✅ YES","❌ NO — adjust assumptions") -> ✅ YES
A18: Moderate scenario covers costs? | B18: =IF(Moderate!B19>0,"✅ YES","❌ NO — adjust assumptions") -> ✅ YES
A19: Optimistic scenario covers costs? | B19: =IF(Optimistic!B19>0,"✅ YES","❌ NO — adjust assumptions") -> ✅ YES
