Workbook

Sheet Settings
A1: ITS — PRICING SETTINGS PANEL
A2: Edit any value here — all other sheets update automatically.
A4: Parameter | B4: Current Value | C4: Unit | D4: Notes
A5: Standard Hourly Rate | B5: 1000 | C5: DA/hr | D5: Billing rate for standard ad-hoc work
A6: Emergency Hourly Rate | B6: 1500 | C6: DA/hr | D6: 1.5x multiplier for emergency call-outs
A7: Dispatch Fee | B7: 2000 | C7: DA | D7: Flat show-up fee for emergency
A8: Minimum Call-Out Fee | B8: 2500 | C8: DA | D8: Minimum charge for non-emergency
A9: Travel Rate (per km) | B9: 150 | C9: DA/km | D9: Outside Skikda zone
A10: Default Materials Markup % | B10: 0.15 | C10: % | D10: Enter as decimal (0.15 = 15%)
A11: Default Risk Buffer % | B11: 0.075 | C11: % | D11: Enter as decimal (0.075 = 7.5%)
A12: Default Target Margin % | B12: 0.25 | C12: % | D12: Enter as decimal (0.25 = 25%)
A13: SLA 12-Month Discount % | B13: 0.1 | C13: % | D13: Enter as decimal (0.10 = 10%)
A14: SLA Basic Monthly Rate | B14: 6000 | C14: DA/mo | D14: Tier 1 — remote monitoring + email
A15: SLA Standard Monthly Rate | B15: 10000 | C15: DA/mo | D15: Tier 2 — Basic + monthly on-site
A16: SLA Comprehensive Rate | B16: 16000 | C16: DA/mo | D16: Tier 3 — priority + reduced emergency

Sheet Fixed Project Quote
A1: FIXED PROJECT QUOTE CALCULATOR
A2: All formulas reference the Settings panel. Override any % below per quote.
A4: Item | B4: Value | C4: Unit
A5: Project Name | B5: e.g. CNC Build - Client X
A6: Estimated Labor Hours | B6: 40 | C6: hours
A7: Standard Hourly Rate | B7: =Settings!B5 | C7: DA
A8: Materials Cost (raw) | B8: 0 | C8: DA
A9: Materials Markup % | B9: =Settings!B10
A10: Risk Buffer % | B10: =Settings!B11
A11: Target Margin % | B11: =Settings!B12
A13: CALCULATED BREAKDOWN
A14: Labor Cost | B14: =B6*B7
A15: Materials + Markup | B15: =B8*(1+B9)
A16: Subtotal | B16: =B14+B15
A17: Risk Buffer Amount | B17: =B16*B10
A18: Total Cost | B18: =B16+B17
A19: Profit Margin | B19: =B18*B11
A20: FINAL QUOTED PRICE | B20: =B18+B19 | C20: DA
A22: STATEMENT OF WORK — QUOTE SUMMARY
A23: Client Name
A24: Project Scope
A25: Payment Terms | B25: Full upon completion
A26: Validity Period | B26: 15 days

Sheet SLA Retainer Builder
A1: SLA RETAINER BUILDER
A2: Rates pulled from Settings. 12-month discount applied automatically.
A4: Tier | B4: Monthly Rate (DA) | C4: Annual Rate (DA) | D4: 12-Month Discounted | E4: You Save | F4: Scope Summary | G4: Min Term
A5: Basic | B5: =Settings!B14 | C5: =B5*12 | D5: =B5*12*(1-Settings!$B$13) | E5: =C5-D5 | F5: Remote monitoring, data logging, priority email support | G5: 6 months
A6: Standard | B6: =Settings!B15 | C6: =B6*12 | D6: =B6*12*(1-Settings!$B$13) | E6: =C6-D6 | F6: Basic + 1 monthly on-site visit (cleaning, calibration) | G6: 6 months
A7: Comprehensive | B7: =Settings!B16 | C7: =B7*12 | D7: =B7*12*(1-Settings!$B$13) | E7: =C7-D7 | F7: Standard + reduced emergency labor + priority scheduling | G7: 12 months
A10: Discount Applied: | B10: =Settings!B13

Sheet Rate Card
A1: ITS — STANDARD RATE CARD
A3: Service | B3: Rate | C3: Notes
A4: Standard Hourly (Ad-hoc, Non-Project) | B4: =Settings!B5 | C4: General troubleshooting, diagnostics
A5: Emergency Hourly (Weekday) | B5: =Settings!B6 | C5: 1.5x multiplier for urgent breakdowns
A6: Emergency Hourly (After-Hours/Weekend) | B6: =Settings!B6 | C6: Same 1.5x multiplier
A7: Dispatch Fee (Emergency) | B7: =Settings!B7 | C7: Flat fee covers mobilization, charged regardless of repair duration
A8: Minimum Call-Out (Non-Emergency) | B8: =Settings!B8 | C8: Minimum charge for any service visit
A9: Travel Outside Skikda Zone | B9: =Settings!B9 | C9: Per kilometer, round trip
A10: Fixed Project Margin Range | B10: 20% - 30% | C10: Target net margin on machine builds & upgrades
A11: SLA Basic Retainer | B11: =Settings!B14 | C11: Monthly — remote monitoring + email support
A12: SLA Standard Retainer | B12: =Settings!B15 | C12: Monthly — Basic + 1 on-site visit
A13: SLA Comprehensive Retainer | B13: =Settings!B16 | C13: Monthly — priority + reduced emergency

Sheet Labor Yield Tracker
A1: LABOR YIELD TRACKER
A2: Target yield: > 1,000 DA/hr. Rows turn red when below target.
A4: Date | B4: Project / Client | C4: Est. Hours | D4: Actual Hours | E4: Revenue (DA) | F4: Yield (DA/hr) | G4: Status
F5: =IF(E5*D5>0, E5/D5, "") | G5: =IF(F5="","",IF(F5>=1000,"✓ On Target","⚠ Below Target"))
F6: =IF(E6*D6>0, E6/D6, "") | G6: =IF(F6="","",IF(F6>=1000,"✓ On Target","⚠ Below Target"))
F7: =IF(E7*D7>0, E7/D7, "") | G7: =IF(F7="","",IF(F7>=1000,"✓ On Target","⚠ Below Target"))
F8: =IF(E8*D8>0, E8/D8, "") | G8: =IF(F8="","",IF(F8>=1000,"✓ On Target","⚠ Below Target"))
F9: =IF(E9*D9>0, E9/D9, "") | G9: =IF(F9="","",IF(F9>=1000,"✓ On Target","⚠ Below Target"))
F10: =IF(E10*D10>0, E10/D10, "") | G10: =IF(F10="","",IF(F10>=1000,"✓ On Target","⚠ Below Target"))
F11: =IF(E11*D11>0, E11/D11, "") | G11: =IF(F11="","",IF(F11>=1000,"✓ On Target","⚠ Below Target"))
F12: =IF(E12*D12>0, E12/D12, "") | G12: =IF(F12="","",IF(F12>=1000,"✓ On Target","⚠ Below Target"))
F13: =IF(E13*D13>0, E13/D13, "") | G13: =IF(F13="","",IF(F13>=1000,"✓ On Target","⚠ Below Target"))
F14: =IF(E14*D14>0, E14/D14, "") | G14: =IF(F14="","",IF(F14>=1000,"✓ On Target","⚠ Below Target"))
F15: =IF(E15*D15>0, E15/D15, "") | G15: =IF(F15="","",IF(F15>=1000,"✓ On Target","⚠ Below Target"))
F16: =IF(E16*D16>0, E16/D16, "") | G16: =IF(F16="","",IF(F16>=1000,"✓ On Target","⚠ Below Target"))
... F24: =IF(E24*D24>0, E24/D24, "") | G24: =IF(F24="","",IF(F24>=1000,"✓ On Target","⚠ Below Target"))
A26: TOTALS | C26: =SUM(D5:D24) | D26: =SUM(D5:D24) | E26: =SUM(E5:E24) | F26: =IF(E26*D26>0, E26/D26, "")

Sheet Breakeven Analysis
A1: BREAKEVEN ANALYSIS
A2: Enter your monthly fixed costs. The sheet calculates minimum billable hours to break even.
A4: Cost Category | B4: Monthly Amount (DA) | D4: Notes
A5: Workshop Rent | B5: 0 | D5: El Harrouch base
A6: Utilities (Elec/Water/Gas) | B6: 0 | D6: Workshop + office
A7: Lead Engineer Salary | B7: 0 | D7: Your draw
A8: Electrical Tech Salary | B8: 0 | D8: Lead Electrical Tech
A9: Mechanical Tech Salary | B9: 0 | D9: Mechanical Building Lead
A10: Generalist Tech Salary | B10: 0 | D10: The Bridge
A11: Vehicle Fuel & Maint. | B11: 0 | D11: Service vehicle
A12: Tool Depreciation | B12: 0 | D12: Diagnostic + machining tools
A13: Safety Gear & Training | B13: 0 | D13: PPE renewals, certifications
A14: Marketing & Materials | B14: 0 | D14: Website, business cards, proposals
A15: Insurance & Licensing | B15: 0 | D15: Liability, professional registration
A16: Miscellaneous | B16: 0 | D16: Buffer for unplanned costs
A18: TOTAL MONTHLY FIXED COSTS | B18: =SUM(B5:B16)
A19: Standard Billing Rate | B19: =Settings!B5
A20: BREAKEVEN — Min Billable Hours/Month | B20: =ROUNDUP(B18/B19, 1)
A21: ≈ Working Days Needed (8hr days) | B21: =ROUNDUP(B20/8, 1)
A23: TIP: Fill in your actual monthly costs above. The breakeven updates instantly.
